{
  "last_scan": "2025-09-26T07:23:29.228549",
  "archives": {
    "data/archives/logs_2025-09-23T06-57-09_2025-09-24T06-56-09.archive": {
      "file_path": "data/archives/logs_2025-09-23T06-57-09_2025-09-24T06-56-09.archive",
      "start_time": "2025-09-23T06:57:09",
      "end_time": "2025-09-24T06:56:09",
      "compression": "gzip",
      "original_size": 2937,
      "compressed_size": 979,
      "record_count": 1000,
      "checksum": "demo_checksum",
      "tags": {
        "source": "demo"
      }
    },
    "data/archives/logs_2025-09-25T07-23-17_2025-09-26T07-22-17.archive": {
      "file_path": "data/archives/logs_2025-09-25T07-23-17_2025-09-26T07-22-17.archive",
      "start_time": "2025-09-25T07:23:17",
      "end_time": "2025-09-26T07:22:17",
      "compression": "gzip",
      "original_size": 2937,
      "compressed_size": 979,
      "record_count": 1000,
      "checksum": "demo_checksum",
      "tags": {
        "source": "demo"
      }
    },
    "data/archives/logs_2025-09-21T06-57-09_2025-09-22T06-56-09.archive": {
      "file_path": "data/archives/logs_2025-09-21T06-57-09_2025-09-22T06-56-09.archive",
      "start_time": "2025-09-21T06:57:09",
      "end_time": "2025-09-22T06:56:09",
      "compression": "gzip",
      "original_size": 2937,
      "compressed_size": 979,
      "record_count": 1000,
      "checksum": "demo_checksum",
      "tags": {
        "source": "demo"
      }
    },
    "data/archives/logs_2025-09-25T07-07-51_2025-09-26T07-06-51.archive": {
      "file_path": "data/archives/logs_2025-09-25T07-07-51_2025-09-26T07-06-51.archive",
      "start_time": "2025-09-25T07:07:51",
      "end_time": "2025-09-26T07:06:51",
      "compression": "gzip",
      "original_size": 2934,
      "compressed_size": 978,
      "record_count": 1000,
      "checksum": "demo_checksum",
      "tags": {
        "source": "demo"
      }
    },
    "data/archives/logs_2025-09-23T06-54-26_2025-09-24T06-53-26.archive": {
      "file_path": "data/archives/logs_2025-09-23T06-54-26_2025-09-24T06-53-26.archive",
      "start_time": "2025-09-23T06:54:26",
      "end_time": "2025-09-24T06:53:26",
      "compression": "gzip",
      "original_size": 2937,
      "compressed_size": 979,
      "record_count": 1000,
      "checksum": "demo_checksum",
      "tags": {
        "source": "demo"
      }
    },
    "data/archives/logs_2025-09-21T06-54-46_2025-09-22T06-53-46.archive": {
      "file_path": "data/archives/logs_2025-09-21T06-54-46_2025-09-22T06-53-46.archive",
      "start_time": "2025-09-21T06:54:46",
      "end_time": "2025-09-22T06:53:46",
      "compression": "gzip",
      "original_size": 2937,
      "compressed_size": 979,
      "record_count": 1000,
      "checksum": "demo_checksum",
      "tags": {
        "source": "demo"
      }
    },
    "data/archives/logs_2025-09-25T06-57-09_2025-09-26T06-56-09.archive": {
      "file_path": "data/archives/logs_2025-09-25T06-57-09_2025-09-26T06-56-09.archive",
      "start_time": "2025-09-25T06:57:09",
      "end_time": "2025-09-26T06:56:09",
      "compression": "gzip",
      "original_size": 2934,
      "compressed_size": 978,
      "record_count": 1000,
      "checksum": "demo_checksum",
      "tags": {
        "source": "demo"
      }
    },
    "data/archives/logs_2025-09-25T07-12-54_2025-09-26T07-11-54.archive": {
      "file_path": "data/archives/logs_2025-09-25T07-12-54_2025-09-26T07-11-54.archive",
      "start_time": "2025-09-25T07:12:54",
      "end_time": "2025-09-26T07:11:54",
      "compression": "gzip",
      "original_size": 2934,
      "compressed_size": 978,
      "record_count": 1000,
      "checksum": "demo_checksum",
      "tags": {
        "source": "demo"
      }
    },
    "data/archives/logs_2025-09-22T06-57-09_2025-09-23T06-56-09.archive": {
      "file_path": "data/archives/logs_2025-09-22T06-57-09_2025-09-23T06-56-09.archive",
      "start_time": "2025-09-22T06:57:09",
      "end_time": "2025-09-23T06:56:09",
      "compression": "gzip",
      "original_size": 2937,
      "compressed_size": 979,
      "record_count": 1000,
      "checksum": "demo_checksum",
      "tags": {
        "source": "demo"
      }
    },
    "data/archives/logs_2025-09-24T07-12-54_2025-09-25T07-11-54.archive": {
      "file_path": "data/archives/logs_2025-09-24T07-12-54_2025-09-25T07-11-54.archive",
      "start_time": "2025-09-24T07:12:54",
      "end_time": "2025-09-25T07:11:54",
      "compression": "gzip",
      "original_size": 2934,
      "compressed_size": 978,
      "record_count": 1000,
      "checksum": "demo_checksum",
      "tags": {
        "source": "demo"
      }
    },
    "data/archives/logs_2025-09-25T07-19-47_2025-09-26T07-18-47.archive": {
      "file_path": "data/archives/logs_2025-09-25T07-19-47_2025-09-26T07-18-47.archive",
      "start_time": "2025-09-25T07:19:47",
      "end_time": "2025-09-26T07:18:47",
      "compression": "gzip",
      "original_size": 2934,
      "compressed_size": 978,
      "record_count": 1000,
      "checksum": "demo_checksum",
      "tags": {
        "source": "demo"
      }
    },
    "data/archives/logs_2025-09-22T07-07-51_2025-09-23T07-06-51.archive": {
      "file_path": "data/archives/logs_2025-09-22T07-07-51_2025-09-23T07-06-51.archive",
      "start_time": "2025-09-22T07:07:51",
      "end_time": "2025-09-23T07:06:51",
      "compression": "gzip",
      "original_size": 2934,
      "compressed_size": 978,
      "record_count": 1000,
      "checksum": "demo_checksum",
      "tags": {
        "source": "demo"
      }
    },
    "data/archives/logs_2025-09-22T06-54-46_2025-09-23T06-53-46.archive": {
      "file_path": "data/archives/logs_2025-09-22T06-54-46_2025-09-23T06-53-46.archive",
      "start_time": "2025-09-22T06:54:46",
      "end_time": "2025-09-23T06:53:46",
      "compression": "gzip",
      "original_size": 2937,
      "compressed_size": 979,
      "record_count": 1000,
      "checksum": "demo_checksum",
      "tags": {
        "source": "demo"
      }
    },
    "data/archives/logs_2025-09-21T07-07-51_2025-09-22T07-06-51.archive": {
      "file_path": "data/archives/logs_2025-09-21T07-07-51_2025-09-22T07-06-51.archive",
      "start_time": "2025-09-21T07:07:51",
      "end_time": "2025-09-22T07:06:51",
      "compression": "gzip",
      "original_size": 2934,
      "compressed_size": 978,
      "record_count": 1000,
      "checksum": "demo_checksum",
      "tags": {
        "source": "demo"
      }
    },
    "data/archives/logs_2025-09-24T06-57-28_2025-09-25T06-56-28.archive": {
      "file_path": "data/archives/logs_2025-09-24T06-57-28_2025-09-25T06-56-28.archive",
      "start_time": "2025-09-24T06:57:28",
      "end_time": "2025-09-25T06:56:28",
      "compression": "gzip",
      "original_size": 2937,
      "compressed_size": 979,
      "record_count": 1000,
      "checksum": "demo_checksum",
      "tags": {
        "source": "demo"
      }
    },
    "data/archives/logs_2025-09-25T06-54-26_2025-09-26T06-53-26.archive": {
      "file_path": "data/archives/logs_2025-09-25T06-54-26_2025-09-26T06-53-26.archive",
      "start_time": "2025-09-25T06:54:26",
      "end_time": "2025-09-26T06:53:26",
      "compression": "gzip",
      "original_size": 2937,
      "compressed_size": 979,
      "record_count": 1000,
      "checksum": "demo_checksum",
      "tags": {
        "source": "demo"
      }
    },
    "data/archives/logs_2025-09-23T07-07-51_2025-09-24T07-06-51.archive": {
      "file_path": "data/archives/logs_2025-09-23T07-07-51_2025-09-24T07-06-51.archive",
      "start_time": "2025-09-23T07:07:51",
      "end_time": "2025-09-24T07:06:51",
      "compression": "gzip",
      "original_size": 2934,
      "compressed_size": 978,
      "record_count": 1000,
      "checksum": "demo_checksum",
      "tags": {
        "source": "demo"
      }
    },
    "data/archives/logs_2025-09-21T07-23-17_2025-09-22T07-22-17.archive": {
      "file_path": "data/archives/logs_2025-09-21T07-23-17_2025-09-22T07-22-17.archive",
      "start_time": "2025-09-21T07:23:17",
      "end_time": "2025-09-22T07:22:17",
      "compression": "gzip",
      "original_size": 2937,
      "compressed_size": 979,
      "record_count": 1000,
      "checksum": "demo_checksum",
      "tags": {
        "source": "demo"
      }
    },
    "data/archives/logs_2025-09-25T06-54-46_2025-09-26T06-53-46.archive": {
      "file_path": "data/archives/logs_2025-09-25T06-54-46_2025-09-26T06-53-46.archive",
      "start_time": "2025-09-25T06:54:46",
      "end_time": "2025-09-26T06:53:46",
      "compression": "gzip",
      "original_size": 2937,
      "compressed_size": 979,
      "record_count": 1000,
      "checksum": "demo_checksum",
      "tags": {
        "source": "demo"
      }
    },
    "data/archives/logs_2025-09-24T07-07-51_2025-09-25T07-06-51.archive": {
      "file_path": "data/archives/logs_2025-09-24T07-07-51_2025-09-25T07-06-51.archive",
      "start_time": "2025-09-24T07:07:51",
      "end_time": "2025-09-25T07:06:51",
      "compression": "gzip",
      "original_size": 2934,
      "compressed_size": 978,
      "record_count": 1000,
      "checksum": "demo_checksum",
      "tags": {
        "source": "demo"
      }
    },
    "data/archives/logs_2025-09-21T07-12-54_2025-09-22T07-11-54.archive": {
      "file_path": "data/archives/logs_2025-09-21T07-12-54_2025-09-22T07-11-54.archive",
      "start_time": "2025-09-21T07:12:54",
      "end_time": "2025-09-22T07:11:54",
      "compression": "gzip",
      "original_size": 2934,
      "compressed_size": 978,
      "record_count": 1000,
      "checksum": "demo_checksum",
      "tags": {
        "source": "demo"
      }
    },
    "data/archives/logs_2025-09-22T06-54-26_2025-09-23T06-53-26.archive": {
      "file_path": "data/archives/logs_2025-09-22T06-54-26_2025-09-23T06-53-26.archive",
      "start_time": "2025-09-22T06:54:26",
      "end_time": "2025-09-23T06:53:26",
      "compression": "gzip",
      "original_size": 2937,
      "compressed_size": 979,
      "record_count": 1000,
      "checksum": "demo_checksum",
      "tags": {
        "source": "demo"
      }
    },
    "data/archives/logs_2025-09-24T07-19-47_2025-09-25T07-18-47.archive": {
      "file_path": "data/archives/logs_2025-09-24T07-19-47_2025-09-25T07-18-47.archive",
      "start_time": "2025-09-24T07:19:47",
      "end_time": "2025-09-25T07:18:47",
      "compression": "gzip",
      "original_size": 2934,
      "compressed_size": 978,
      "record_count": 1000,
      "checksum": "demo_checksum",
      "tags": {
        "source": "demo"
      }
    },
    "data/archives/logs_2025-09-24T07-23-17_2025-09-25T07-22-17.archive": {
      "file_path": "data/archives/logs_2025-09-24T07-23-17_2025-09-25T07-22-17.archive",
      "start_time": "2025-09-24T07:23:17",
      "end_time": "2025-09-25T07:22:17",
      "compression": "gzip",
      "original_size": 2937,
      "compressed_size": 979,
      "record_count": 1000,
      "checksum": "demo_checksum",
      "tags": {
        "source": "demo"
      }
    },
    "data/archives/logs_2025-09-23T07-19-47_2025-09-24T07-18-47.archive": {
      "file_path": "data/archives/logs_2025-09-23T07-19-47_2025-09-24T07-18-47.archive",
      "start_time": "2025-09-23T07:19:47",
      "end_time": "2025-09-24T07:18:47",
      "compression": "gzip",
      "original_size": 2934,
      "compressed_size": 978,
      "record_count": 1000,
      "checksum": "demo_checksum",
      "tags": {
        "source": "demo"
      }
    },
    "data/archives/logs_2025-09-25T06-57-28_2025-09-26T06-56-28.archive": {
      "file_path": "data/archives/logs_2025-09-25T06-57-28_2025-09-26T06-56-28.archive",
      "start_time": "2025-09-25T06:57:28",
      "end_time": "2025-09-26T06:56:28",
      "compression": "gzip",
      "original_size": 2937,
      "compressed_size": 979,
      "record_count": 1000,
      "checksum": "demo_checksum",
      "tags": {
        "source": "demo"
      }
    },
    "data/archives/logs_2025-09-22T06-57-28_2025-09-23T06-56-28.archive": {
      "file_path": "data/archives/logs_2025-09-22T06-57-28_2025-09-23T06-56-28.archive",
      "start_time": "2025-09-22T06:57:28",
      "end_time": "2025-09-23T06:56:28",
      "compression": "gzip",
      "original_size": 2937,
      "compressed_size": 979,
      "record_count": 1000,
      "checksum": "demo_checksum",
      "tags": {
        "source": "demo"
      }
    },
    "data/archives/logs_2025-09-24T06-57-09_2025-09-25T06-56-09.archive": {
      "file_path": "data/archives/logs_2025-09-24T06-57-09_2025-09-25T06-56-09.archive",
      "start_time": "2025-09-24T06:57:09",
      "end_time": "2025-09-25T06:56:09",
      "compression": "gzip",
      "original_size": 2937,
      "compressed_size": 979,
      "record_count": 1000,
      "checksum": "demo_checksum",
      "tags": {
        "source": "demo"
      }
    },
    "data/archives/logs_2025-09-24T06-54-26_2025-09-25T06-53-26.archive": {
      "file_path": "data/archives/logs_2025-09-24T06-54-26_2025-09-25T06-53-26.archive",
      "start_time": "2025-09-24T06:54:26",
      "end_time": "2025-09-25T06:53:26",
      "compression": "gzip",
      "original_size": 2937,
      "compressed_size": 979,
      "record_count": 1000,
      "checksum": "demo_checksum",
      "tags": {
        "source": "demo"
      }
    },
    "data/archives/logs_2025-09-22T07-12-54_2025-09-23T07-11-54.archive": {
      "file_path": "data/archives/logs_2025-09-22T07-12-54_2025-09-23T07-11-54.archive",
      "start_time": "2025-09-22T07:12:54",
      "end_time": "2025-09-23T07:11:54",
      "compression": "gzip",
      "original_size": 2934,
      "compressed_size": 978,
      "record_count": 1000,
      "checksum": "demo_checksum",
      "tags": {
        "source": "demo"
      }
    },
    "data/archives/logs_2025-09-23T07-12-54_2025-09-24T07-11-54.archive": {
      "file_path": "data/archives/logs_2025-09-23T07-12-54_2025-09-24T07-11-54.archive",
      "start_time": "2025-09-23T07:12:54",
      "end_time": "2025-09-24T07:11:54",
      "compression": "gzip",
      "original_size": 2934,
      "compressed_size": 978,
      "record_count": 1000,
      "checksum": "demo_checksum",
      "tags": {
        "source": "demo"
      }
    },
    "data/archives/logs_2025-09-24T06-58-20_2025-09-25T06-57-20.archive": {
      "file_path": "data/archives/logs_2025-09-24T06-58-20_2025-09-25T06-57-20.archive",
      "start_time": "2025-09-24T06:58:20",
      "end_time": "2025-09-25T06:57:20",
      "compression": "gzip",
      "original_size": 2937,
      "compressed_size": 979,
      "record_count": 1000,
      "checksum": "demo_checksum",
      "tags": {
        "source": "demo"
      }
    },
    "data/archives/logs_2025-09-21T07-19-47_2025-09-22T07-18-47.archive": {
      "file_path": "data/archives/logs_2025-09-21T07-19-47_2025-09-22T07-18-47.archive",
      "start_time": "2025-09-21T07:19:47",
      "end_time": "2025-09-22T07:18:47",
      "compression": "gzip",
      "original_size": 2934,
      "compressed_size": 978,
      "record_count": 1000,
      "checksum": "demo_checksum",
      "tags": {
        "source": "demo"
      }
    },
    "data/archives/logs_2025-09-25T06-58-20_2025-09-26T06-57-20.archive": {
      "file_path": "data/archives/logs_2025-09-25T06-58-20_2025-09-26T06-57-20.archive",
      "start_time": "2025-09-25T06:58:20",
      "end_time": "2025-09-26T06:57:20",
      "compression": "gzip",
      "original_size": 2937,
      "compressed_size": 979,
      "record_count": 1000,
      "checksum": "demo_checksum",
      "tags": {
        "source": "demo"
      }
    },
    "data/archives/logs_2025-09-23T06-57-28_2025-09-24T06-56-28.archive": {
      "file_path": "data/archives/logs_2025-09-23T06-57-28_2025-09-24T06-56-28.archive",
      "start_time": "2025-09-23T06:57:28",
      "end_time": "2025-09-24T06:56:28",
      "compression": "gzip",
      "original_size": 2937,
      "compressed_size": 979,
      "record_count": 1000,
      "checksum": "demo_checksum",
      "tags": {
        "source": "demo"
      }
    },
    "data/archives/logs_2025-09-21T06-58-20_2025-09-22T06-57-20.archive": {
      "file_path": "data/archives/logs_2025-09-21T06-58-20_2025-09-22T06-57-20.archive",
      "start_time": "2025-09-21T06:58:20",
      "end_time": "2025-09-22T06:57:20",
      "compression": "gzip",
      "original_size": 2937,
      "compressed_size": 979,
      "record_count": 1000,
      "checksum": "demo_checksum",
      "tags": {
        "source": "demo"
      }
    },
    "data/archives/logs_2025-09-23T07-23-17_2025-09-24T07-22-17.archive": {
      "file_path": "data/archives/logs_2025-09-23T07-23-17_2025-09-24T07-22-17.archive",
      "start_time": "2025-09-23T07:23:17",
      "end_time": "2025-09-24T07:22:17",
      "compression": "gzip",
      "original_size": 2934,
      "compressed_size": 978,
      "record_count": 1000,
      "checksum": "demo_checksum",
      "tags": {
        "source": "demo"
      }
    },
    "data/archives/logs_2025-09-22T07-23-17_2025-09-23T07-22-17.archive": {
      "file_path": "data/archives/logs_2025-09-22T07-23-17_2025-09-23T07-22-17.archive",
      "start_time": "2025-09-22T07:23:17",
      "end_time": "2025-09-23T07:22:17",
      "compression": "gzip",
      "original_size": 2934,
      "compressed_size": 978,
      "record_count": 1000,
      "checksum": "demo_checksum",
      "tags": {
        "source": "demo"
      }
    },
    "data/archives/logs_2025-09-24T06-54-46_2025-09-25T06-53-46.archive": {
      "file_path": "data/archives/logs_2025-09-24T06-54-46_2025-09-25T06-53-46.archive",
      "start_time": "2025-09-24T06:54:46",
      "end_time": "2025-09-25T06:53:46",
      "compression": "gzip",
      "original_size": 2937,
      "compressed_size": 979,
      "record_count": 1000,
      "checksum": "demo_checksum",
      "tags": {
        "source": "demo"
      }
    },
    "data/archives/logs_2025-09-23T06-54-46_2025-09-24T06-53-46.archive": {
      "file_path": "data/archives/logs_2025-09-23T06-54-46_2025-09-24T06-53-46.archive",
      "start_time": "2025-09-23T06:54:46",
      "end_time": "2025-09-24T06:53:46",
      "compression": "gzip",
      "original_size": 2937,
      "compressed_size": 979,
      "record_count": 1000,
      "checksum": "demo_checksum",
      "tags": {
        "source": "demo"
      }
    },
    "data/archives/logs_2025-09-21T06-57-28_2025-09-22T06-56-28.archive": {
      "file_path": "data/archives/logs_2025-09-21T06-57-28_2025-09-22T06-56-28.archive",
      "start_time": "2025-09-21T06:57:28",
      "end_time": "2025-09-22T06:56:28",
      "compression": "gzip",
      "original_size": 2937,
      "compressed_size": 979,
      "record_count": 1000,
      "checksum": "demo_checksum",
      "tags": {
        "source": "demo"
      }
    },
    "data/archives/logs_2025-09-22T07-19-47_2025-09-23T07-18-47.archive": {
      "file_path": "data/archives/logs_2025-09-22T07-19-47_2025-09-23T07-18-47.archive",
      "start_time": "2025-09-22T07:19:47",
      "end_time": "2025-09-23T07:18:47",
      "compression": "gzip",
      "original_size": 2934,
      "compressed_size": 978,
      "record_count": 1000,
      "checksum": "demo_checksum",
      "tags": {
        "source": "demo"
      }
    },
    "data/archives/logs_2025-09-21T06-54-26_2025-09-22T06-53-26.archive": {
      "file_path": "data/archives/logs_2025-09-21T06-54-26_2025-09-22T06-53-26.archive",
      "start_time": "2025-09-21T06:54:26",
      "end_time": "2025-09-22T06:53:26",
      "compression": "gzip",
      "original_size": 2937,
      "compressed_size": 979,
      "record_count": 1000,
      "checksum": "demo_checksum",
      "tags": {
        "source": "demo"
      }
    },
    "data/archives/logs_2025-09-22T06-58-20_2025-09-23T06-57-20.archive": {
      "file_path": "data/archives/logs_2025-09-22T06-58-20_2025-09-23T06-57-20.archive",
      "start_time": "2025-09-22T06:58:20",
      "end_time": "2025-09-23T06:57:20",
      "compression": "gzip",
      "original_size": 2937,
      "compressed_size": 979,
      "record_count": 1000,
      "checksum": "demo_checksum",
      "tags": {
        "source": "demo"
      }
    },
    "data/archives/logs_2025-09-23T06-58-20_2025-09-24T06-57-20.archive": {
      "file_path": "data/archives/logs_2025-09-23T06-58-20_2025-09-24T06-57-20.archive",
      "start_time": "2025-09-23T06:58:20",
      "end_time": "2025-09-24T06:57:20",
      "compression": "gzip",
      "original_size": 2937,
      "compressed_size": 979,
      "record_count": 1000,
      "checksum": "demo_checksum",
      "tags": {
        "source": "demo"
      }
    }
  }
}